testing_pubsub/__init__.py
testing_pubsub/pubsub.py
testing_pubsub-0.0.6.dist-info/LICENSE
testing_pubsub-0.0.6.dist-info/METADATA
testing_pubsub-0.0.6.dist-info/WHEEL
testing_pubsub-0.0.6.dist-info/top_level.txt
testing_pubsub-0.0.6.dist-info/RECORD
